README.rst
setup.cfg
setup.py
django_admin_smoke_tests/__init__.py
django_admin_smoke_tests/tests.py
django_admin_smoke_tests_2.egg-info/PKG-INFO
django_admin_smoke_tests_2.egg-info/SOURCES.txt
django_admin_smoke_tests_2.egg-info/dependency_links.txt
django_admin_smoke_tests_2.egg-info/not-zip-safe
django_admin_smoke_tests_2.egg-info/requires.txt
django_admin_smoke_tests_2.egg-info/top_level.txt