Metadata-Version: 1.1
Name: django-admin-smoke-tests-2
Version: 0.3.1
Summary: Runs some quick tests on your admin site objects to make sure there aren't non-existant fields listed, etc.
Home-page: https://github.com/SeanHayes/django-admin-smoke-tests
Author: Seán Hayes
Author-email: sean@seanhayes.name
License: BSD
Download-URL: https://github.com/SeanHayes/django-admin-smoke-tests
Keywords: django admin smoke test
Platform: UNKNOWN
Classifier: Development Status :: 3 - Alpha
Classifier: Intended Audience :: Developers
Classifier: License :: OSI Approved :: BSD License
Classifier: Programming Language :: Python
Classifier: Topic :: Software Development :: Build Tools
Classifier: Topic :: Software Development :: Libraries
Classifier: Topic :: Software Development :: Libraries :: Python Modules
